__init__.py
omi_tools/__init__.py
omi_tools/metrics.py
omi_tools/plots.py
omi_tools/transformations.py
omi_tools-0.0.3.dist-info/LICENSE
omi_tools-0.0.3.dist-info/METADATA
omi_tools-0.0.3.dist-info/WHEEL
omi_tools-0.0.3.dist-info/top_level.txt
omi_tools-0.0.3.dist-info/RECORD
