Metadata-Version: 2.1
Name: omi_tools
Version: 0.0.3
Summary: Package with various utilities for OMI department
Author-email: Věnceslav Chumchal <venceslav.chumchal@tul.cz>
Project-URL: Homepage, https://gitlab.com/omi4095002/omi-tools
Project-URL: Issues, https://gitlab.com/omi4095002/omi-tools/issues
Classifier: Programming Language :: Python :: 3
Classifier: License :: OSI Approved :: MIT License
Classifier: Operating System :: OS Independent
Requires-Python: >=3.8
License-File: LICENSE
Requires-Dist: matplotlib
Requires-Dist: pandas
Requires-Dist: scipy
Requires-Dist: symfit
Requires-Dist: PyWavelet
